adk_agent_sim/__init__.py
adk_agent_sim/plugin/__init__.py
adk_agent_sim/plugin/client_factory.py
adk_agent_sim/plugin/config.py
adk_agent_sim/plugin/converter.py
adk_agent_sim/plugin/core.py
adk_agent_sim/plugin/futures.py
adk_agent_sim-0.1.22.dist-info/METADATA
adk_agent_sim-0.1.22.dist-info/WHEEL
adk_agent_sim-0.1.22.dist-info/RECORD
