Metadata-Version: 2.4
Name: adk-agent-sim
Version: 0.1.22
Summary: ADK Agent Simulator - Python Plugin
Requires-Python: >=3.14
Requires-Dist: adk-sim-protos==0.1.22
Requires-Dist: google-adk>=1.21.0
Requires-Dist: grpclib>=0.4.7
